{"id":1352,"map":{"projection":"World","legendStepSize":20,"colorSchemeLabels":[],"colorSchemeValues":[],"defaultProjection":"World","customNumericColors":[],"customCategoryColors":{},"customCategoryLabels":{},"customHiddenCategories":{}},"tab":"chart","slug":"food-waste-by-country-in-the-european-union","type":"DiscreteBar","title":"Food waste by country in the European Union","xAxis":{"scaleType":"linear"},"yAxis":{"min":0,"scaleType":"linear"},"subtitle":"Annual food wastage across the supply chain by country in the European Union, measured in tonnes per year.","hasMapTab":false,"originUrl":"","stackMode":"absolute","dimensions":[{"id":8509,"unit":null,"order":0,"chartId":1352,"property":"y","shortUnit":"tonnes","tolerance":null,"targetYear":null,"variableId":42664,"displayName":null,"isProjection":null,"conversionFactor":null}],"isAutoSlug":true,"hasChartTab":true,"isPublished":true,"selectedData":[{"index":0,"entityId":212},{"index":0,"entityId":161},{"index":0,"entityId":156},{"index":0,"entityId":24},{"index":0,"entityId":4},{"index":0,"entityId":39},{"index":0,"entityId":163},{"index":0,"entityId":162},{"index":0,"entityId":318},{"index":0,"entityId":155},{"index":0,"entityId":3},{"index":0,"entityId":6},{"index":0,"entityId":149},{"index":0,"entityId":138},{"index":0,"entityId":2},{"index":0,"entityId":8},{"index":0,"entityId":122},{"index":0,"entityId":119},{"index":0,"entityId":210},{"index":0,"entityId":5},{"index":0,"entityId":11},{"index":0,"entityId":95},{"index":0,"entityId":92},{"index":0,"entityId":85},{"index":0,"entityId":83},{"index":0,"entityId":9},{"index":0,"entityId":10},{"index":0,"entityId":1}],"internalNotes":"","addCountryMode":"add-country","hideTitleAnnotation":true}