{"id":684,"map":{"mode":"specific","projection":"World","targetYear":1980,"timeRanges":[],"variableId":72,"defaultYear":1980,"isColorblind":false,"timelineMode":"slider","timeTolerance":1,"legendStepSize":20,"targetYearMode":"latest","baseColorScheme":"BuGn","colorSchemeInvert":false,"colorSchemeLabels":[],"colorSchemeValues":[],"defaultProjection":"World","legendDescription":"","legendOrientation":"portrait","customColorsActive":false,"customNumericColors":[],"customCategoryColors":{},"customCategoryLabels":{},"customHiddenCategories":{}},"tab":"chart","note":"","slug":"how-much-we-think-we-spend-on-healthcare-vs-how-much-we-actually-do","type":"ScatterPlot","logos":["OWD"],"title":"How much we think we spend on healthcare vs. how much we actually do","units":"[{\"property\":\"x\",\"visible\":true,\"title\":\"Real spending\",\"unit\":\"% of gross domestic product (GDP)\",\"format\":\"\"},{\"property\":\"y\",\"visible\":true,\"title\":\"Guessed spending\",\"unit\":\"% of gross domestic product (GDP)\",\"format\":\"\"},{\"property\":\"size\",\"visible\":false,\"title\":\"\",\"unit\":\"\",\"format\":\"\"}]","xAxis":{"max":40,"suffix":"%","scaleType":"linear"},"yAxis":{"min":0,"suffix":"%","scaleType":"linear","labelDistance":-10},"margins":{"top":10,"left":60,"right":10,"bottom":10},"version":1,"subtitle":"How much we think we spend on health expenditure measured against how much we actually spend (both measured in terms of percentage of gross domestic product, GDP, per year).","timeline":null,"hasMapTab":false,"originUrl":"https://ourworldindata.org/financing-healthcare/","stackMode":null,"dimensions":[{"id":1428,"unit":"% of gross domestic product (GDP)","order":0,"chartId":684,"property":"x","shortUnit":null,"tolerance":5,"targetYear":null,"variableId":1979,"displayName":"How much we actually spend on health expenditure (% of GDP)","isProjection":false,"conversionFactor":null},{"id":1429,"unit":"% of gross domestic product (GDP)","order":1,"chartId":684,"property":"y","shortUnit":null,"tolerance":5,"targetYear":null,"variableId":1978,"displayName":"How much we think we spend on health expenditure (% of GDP)","isProjection":false,"conversionFactor":null},{"id":1430,"unit":"","order":2,"chartId":684,"property":"size","shortUnit":null,"tolerance":5,"targetYear":null,"variableId":72,"displayName":"","isProjection":false,"conversionFactor":null},{"property":"color","variableId":123}],"entityType":"country","hideLegend":true,"sourceDesc":"Ipsos MORI Perils of Perception 2016","hasChartTab":true,"isPublished":true,"hideTimeline":true,"identityLine":false,"selectedData":[],"internalNotes":"","addCountryMode":"add-country","comparisonLine":{},"activeLegendKeys":null,"group-by-variables":false,"hideRelativeToggle":false}