{"id":1650,"map":{"projection":"World","variableId":65417,"baseColorScheme":"RdPu","isManualBuckets":true,"colorSchemeLabels":[],"colorSchemeValues":[2,4,6,8,10,12,14,16],"defaultProjection":"World","colorSchemeMinValue":0,"customNumericColors":[],"customCategoryColors":{},"customCategoryLabels":{},"customHiddenCategories":{}},"tab":"chart","slug":"percentage-of-women-18-to-29-who-report-having-been-victims-of-forced-sex-as-children","type":"DiscreteBar","title":"Percentage of women (18 to 29) who report having been victims of forced sex as children","xAxis":{"scaleType":"linear"},"yAxis":{"min":0,"scaleType":"linear"},"subtitle":"Percentage of women aged 18 to 29 years who report having experienced forced sex before the age of 18. Estimates come from surveys in the period 2005–2016. Forced sex includes sexual intercourse or any other sexual acts that were forced, physically or in any other way.","hasMapTab":true,"originUrl":"https://ourworldindata.org/violence-against-rights-for-children/","stackMode":"absolute","dimensions":[{"property":"y","variableId":65417}],"hasChartTab":true,"isPublished":true,"selectedData":[{"index":0,"entityId":43},{"index":0,"entityId":107},{"index":0,"entityId":15},{"index":0,"entityId":42},{"index":0,"entityId":173},{"index":0,"entityId":170},{"index":0,"entityId":35115},{"index":0,"entityId":158},{"index":0,"entityId":117},{"index":0,"entityId":150},{"index":0,"entityId":145},{"index":0,"entityId":129},{"index":0,"entityId":109},{"index":0,"entityId":142},{"index":0,"entityId":103},{"index":0,"entityId":91},{"index":0,"entityId":87},{"index":0,"entityId":76},{"index":0,"entityId":64},{"index":0,"entityId":68},{"index":0,"entityId":60},{"index":0,"entityId":80}],"internalNotes":"","addCountryMode":"add-country","hideTitleAnnotation":true}