{"id":975,"map":{"mode":"specific","projection":"World","targetYear":1980,"timeRanges":[],"variableId":8727,"defaultYear":1980,"isColorblind":false,"timelineMode":"slider","timeTolerance":1,"legendStepSize":20,"targetYearMode":"latest","baseColorScheme":"BuGn","colorSchemeInvert":false,"colorSchemeLabels":[],"colorSchemeValues":[],"defaultProjection":"World","legendDescription":"","legendOrientation":"portrait","customColorsActive":false,"customNumericColors":[],"customCategoryColors":{},"customCategoryLabels":{},"customHiddenCategories":{}},"tab":"chart","note":"","slug":"projections-for-global-peak-agricultural-land","type":"LineChart","logos":["OWD"],"title":"Projections for global peak agricultural land","units":"[{\"property\":\"y\",\"visible\":true,\"title\":\"\",\"unit\":\"hectares\",\"format\":\"\"}]","xAxis":{"scaleType":"linear"},"yAxis":{"min":0,"suffix":" ha","scaleType":"linear","labelDistance":-10},"margins":{"top":10,"left":60,"right":10,"bottom":10},"maxTime":2050,"minTime":1980,"version":1,"subtitle":"Projected trends in global agricultural area extent by various sources, measured in hectares. Projections include those from the UN Food and Agricultural Organization (FAO), International Assessment of Agricultural Knowledge, Science and Technology for Development (IAASTD); OECD, and scenarios from the Millennium Ecosystem Assessment (MEA). Also shown is the actual agricultural area to 2014, as reported by the UN FAO.","timeline":null,"hasMapTab":false,"originUrl":"https://ourworldindata.org/wp-content/uploads/2013/03/Share-of-US-households-with-basic-electrical-appliances-with-working-hours-2-750x525.png","stackMode":null,"dimensions":[{"id":4213,"unit":"hectares","order":0,"chartId":975,"property":"y","shortUnit":null,"tolerance":5,"targetYear":null,"variableId":8727,"displayName":"Measured agricultural area","isProjection":false,"conversionFactor":null},{"id":4214,"unit":"hectares","order":1,"chartId":975,"property":"y","shortUnit":null,"tolerance":5,"targetYear":null,"variableId":8728,"displayName":"FAO/IMAGE","isProjection":true,"conversionFactor":null},{"id":4215,"unit":"hectares","order":2,"chartId":975,"property":"y","shortUnit":null,"tolerance":5,"targetYear":null,"variableId":8729,"displayName":"IAASTD","isProjection":true,"conversionFactor":null},{"id":4216,"unit":"hectares","order":3,"chartId":975,"property":"y","shortUnit":null,"tolerance":5,"targetYear":null,"variableId":8730,"displayName":"OECD Outlook","isProjection":true,"conversionFactor":null},{"id":4217,"unit":"hectares","order":4,"chartId":975,"property":"y","shortUnit":null,"tolerance":5,"targetYear":null,"variableId":8731,"displayName":"MEA Scenario 1","isProjection":true,"conversionFactor":null},{"id":4218,"unit":"hectares","order":5,"chartId":975,"property":"y","shortUnit":null,"tolerance":5,"targetYear":null,"variableId":8732,"displayName":"MEA Scenario 2","isProjection":true,"conversionFactor":null},{"id":4219,"unit":"hectares","order":6,"chartId":975,"property":"y","shortUnit":null,"tolerance":5,"targetYear":null,"variableId":8733,"displayName":"MEA Scenario 3","isProjection":true,"conversionFactor":null},{"id":4220,"unit":"hectares","order":7,"chartId":975,"property":"y","shortUnit":null,"tolerance":5,"targetYear":null,"variableId":8734,"displayName":"MEA Scenario 4","isProjection":true,"conversionFactor":null}],"entityType":"country","hideLegend":false,"hasChartTab":true,"isPublished":true,"identityLine":false,"selectedData":[{"color":"#818282","index":0,"entityId":355},{"index":1,"entityId":355},{"index":2,"entityId":355},{"index":3,"entityId":355},{"index":4,"entityId":355},{"index":5,"entityId":355},{"index":6,"entityId":355},{"index":7,"entityId":355}],"internalNotes":"","addCountryMode":"add-country","activeLegendKeys":null,"group-by-variables":false,"hideRelativeToggle":false,"hideTitleAnnotation":true}