{"id":1541,"map":{"projection":"World","legendStepSize":20,"colorSchemeLabels":[],"colorSchemeValues":[],"defaultProjection":"World","colorSchemeMinValue":0,"customNumericColors":[],"customCategoryColors":{},"customCategoryLabels":{},"customHiddenCategories":{}},"tab":"chart","slug":"resource-socioeconomic-change","type":"LineChart","title":"Resource and socioeconomic change","xAxis":{"scaleType":"linear"},"yAxis":{"min":0,"scaleType":"linear"},"version":1,"subtitle":"Change across various socioeconomic and environmental parameters over the past 50 years, measured as an index relative to the year 1965 (i.e. values in 1965 =100).","hasMapTab":false,"originUrl":"","stackMode":"absolute","dimensions":[{"id":10492,"unit":null,"order":0,"chartId":1541,"property":"y","shortUnit":null,"tolerance":null,"targetYear":null,"variableId":43084,"displayName":null,"isProjection":null,"conversionFactor":null},{"id":10493,"unit":null,"order":1,"chartId":1541,"property":"y","shortUnit":null,"tolerance":null,"targetYear":null,"variableId":43085,"displayName":null,"isProjection":null,"conversionFactor":null},{"id":10494,"unit":null,"order":2,"chartId":1541,"property":"y","shortUnit":null,"tolerance":null,"targetYear":null,"variableId":43082,"displayName":null,"isProjection":null,"conversionFactor":null},{"id":10495,"unit":null,"order":3,"chartId":1541,"property":"y","shortUnit":null,"tolerance":null,"targetYear":null,"variableId":43083,"displayName":null,"isProjection":null,"conversionFactor":null},{"id":10496,"unit":null,"order":4,"chartId":1541,"property":"y","shortUnit":null,"tolerance":null,"targetYear":null,"variableId":43086,"displayName":null,"isProjection":null,"conversionFactor":null},{"id":10497,"unit":null,"order":5,"chartId":1541,"property":"y","shortUnit":null,"tolerance":null,"targetYear":null,"variableId":43087,"displayName":null,"isProjection":null,"conversionFactor":null},{"id":10498,"unit":null,"order":6,"chartId":1541,"property":"y","shortUnit":null,"tolerance":null,"targetYear":null,"variableId":43088,"displayName":null,"isProjection":null,"conversionFactor":null},{"id":10499,"unit":null,"order":7,"chartId":1541,"property":"y","shortUnit":null,"tolerance":null,"targetYear":null,"variableId":43089,"displayName":null,"isProjection":null,"conversionFactor":null},{"id":10500,"unit":null,"order":8,"chartId":1541,"property":"y","shortUnit":null,"tolerance":null,"targetYear":null,"variableId":43090,"displayName":null,"isProjection":null,"conversionFactor":null},{"id":10501,"unit":null,"order":9,"chartId":1541,"property":"y","shortUnit":null,"tolerance":null,"targetYear":null,"variableId":43091,"displayName":null,"isProjection":null,"conversionFactor":null},{"id":10502,"unit":null,"order":10,"chartId":1541,"property":"y","shortUnit":null,"tolerance":null,"targetYear":null,"variableId":43092,"displayName":null,"isProjection":null,"conversionFactor":null},{"id":10503,"unit":null,"order":11,"chartId":1541,"property":"y","shortUnit":null,"tolerance":null,"targetYear":null,"variableId":43093,"displayName":null,"isProjection":null,"conversionFactor":null},{"id":10504,"unit":null,"order":12,"chartId":1541,"property":"y","shortUnit":null,"tolerance":null,"targetYear":null,"variableId":43107,"displayName":null,"isProjection":null,"conversionFactor":null},{"id":10505,"unit":null,"order":13,"chartId":1541,"property":"y","shortUnit":null,"tolerance":null,"targetYear":null,"variableId":43108,"displayName":null,"isProjection":null,"conversionFactor":null},{"id":10506,"unit":null,"order":14,"chartId":1541,"property":"y","shortUnit":null,"tolerance":null,"targetYear":null,"variableId":43105,"displayName":null,"isProjection":null,"conversionFactor":null},{"id":10507,"unit":null,"order":15,"chartId":1541,"property":"y","shortUnit":null,"tolerance":null,"targetYear":null,"variableId":43109,"displayName":null,"isProjection":null,"conversionFactor":null}],"entityType":"data","hasChartTab":true,"isPublished":true,"selectedData":[{"index":0,"entityId":171},{"index":1,"entityId":171},{"index":10,"entityId":171},{"index":11,"entityId":171},{"index":12,"entityId":171},{"index":13,"entityId":171},{"index":14,"entityId":171},{"index":3,"entityId":171},{"index":4,"entityId":171},{"index":5,"entityId":171},{"index":6,"entityId":171},{"index":7,"entityId":171},{"index":8,"entityId":171},{"index":9,"entityId":171}],"internalNotes":"","addCountryMode":"change-country"}