{"id":40,"map":{"projection":"World","targetYear":2000,"variableId":19,"timeTolerance":10,"legendStepSize":20,"baseColorScheme":"BuGn","isManualBuckets":true,"colorSchemeLabels":[],"colorSchemeValues":[],"defaultProjection":"World","legendDescription":"","customNumericColors":["#000","#c00","#0c0","#00c","#c0c"],"customCategoryColors":{},"customCategoryLabels":{},"customHiddenCategories":{}},"tab":"chart","note":"","slug":"scatterplot-of-national-suicide-rates-and-mean-years-of-schooling-in-population-over-age-15","type":"ScatterPlot","title":"National suicide rates and mean years of schooling in population over age 15","xAxis":{"scaleType":"linear"},"yAxis":{"max":36,"min":0,"scaleType":"linear"},"maxTime":2005,"minTime":2005,"version":1,"hasMapTab":false,"originUrl":"https://ourworldindata.org/suicide/","stackMode":null,"dimensions":[{"id":6760,"unit":"years","order":0,"chartId":40,"property":"x","shortUnit":null,"tolerance":10,"targetYear":null,"variableId":357,"displayName":"Barro Lee Education Dataset: Educational Attainment (average years of total education)","isProjection":false,"conversionFactor":null},{"id":6761,"unit":null,"order":1,"chartId":40,"property":"y","shortUnit":null,"tolerance":10,"targetYear":null,"variableId":19,"displayName":"suicide rate","isProjection":false,"conversionFactor":null},{"property":"color","variableId":123},{"property":"size","variableId":72}],"entityType":"country","hideLegend":true,"hasChartTab":true,"isPublished":true,"hideTimeline":true,"selectedData":[],"internalNotes":"","addCountryMode":"add-country","hideRelativeToggle":false}