{"id":1793,"map":{"projection":"World","targetYear":2016,"variableId":3053,"legendStepSize":20,"baseColorScheme":"YlOrBr","colorSchemeLabels":[],"colorSchemeValues":[],"defaultProjection":"World","legendDescription":"Unemployment rate (% of total labour force)","colorSchemeMinValue":0,"customNumericColors":[],"customCategoryColors":{},"customCategoryLabels":{},"customHiddenCategories":{}},"tab":"map","slug":"unemployment-rate","type":"LineChart","title":"Unemployment rate (% of total labour force)","xAxis":{"scaleType":"linear"},"yAxis":{"min":0,"scaleType":"linear"},"subtitle":"Unemployment refers to the share of the labor force that is without work but available for and seeking employment. There may be persons not currently in the labour market who want to work but do not actively \"seek\" work because they view job opportunities as limited, or because they have restricted labour mobility, or face discrimination, or structural, social or cultural barriers. The exclusion of people who want to work but are not seeking work (often called the \"hidden unemployed\" or \"discouraged workers\") is a criterion that will affect the unemployment count of both women and men. ","hasMapTab":true,"originUrl":"","stackMode":"absolute","dimensions":[{"id":12739,"unit":null,"order":0,"chartId":1793,"property":"y","shortUnit":null,"tolerance":null,"targetYear":null,"variableId":3053,"displayName":null,"isProjection":null,"conversionFactor":null}],"hasChartTab":true,"isPublished":true,"selectedData":[{"index":0,"entityId":174},{"index":0,"entityId":5},{"index":0,"entityId":28},{"index":0,"entityId":13},{"index":0,"entityId":44},{"index":0,"entityId":170},{"index":0,"entityId":10},{"index":0,"entityId":171}],"internalNotes":"","addCountryMode":"add-country"}