{"id":303,"map":{"mode":"specific","maxYear":2000,"minYear":1980,"projection":"World","targetYear":1980,"timeRanges":[],"variableId":1324,"defaultYear":1980,"isColorblind":false,"timelineMode":"timeline","timeTolerance":1,"legendStepSize":20,"targetYearMode":"normal","baseColorScheme":"BuGn","colorSchemeName":"BuGn","colorSchemeInvert":false,"colorSchemeLabels":[],"defaultProjection":"World","legendDescription":"","legendOrientation":"portrait","customNumericColors":[]},"tab":"chart","slug":"world-pop-by-political-regime","type":"StackedArea","logos":["OWD"],"title":"Number of world citizens living under different political regimes","units":"[{\"property\":\"y\",\"visible\":true,\"title\":\"\",\"unit\":\"People\",\"format\":\"\"}]","xAxis":{"scaleType":"linear"},"yAxis":{"min":0,"scaleType":"linear","labelDistance":-10},"margins":{"top":"10","left":"110","right":"10","bottom":"10"},"subtitle":"The Polity IV score captures the type of political regime for each country on a range  from -10 (full autocracy) to +10 (full democracy). Regimes that fall into the middle of this spectrum are called anocracies.","timeline":null,"hasMapTab":false,"originUrl":"https://ourworldindata.org/a-history-of-global-living-conditions-in-5-charts/","stackMode":"absolute","dimensions":[{"id":310,"unit":"People","order":0,"chartId":303,"property":"y","shortUnit":null,"tolerance":5,"targetYear":null,"variableId":1324,"displayName":"Country in Transition or No Data","isProjection":false,"conversionFactor":null},{"id":311,"unit":"People","order":1,"chartId":303,"property":"y","shortUnit":null,"tolerance":5,"targetYear":null,"variableId":1325,"displayName":"Population in Colony","isProjection":false,"conversionFactor":null},{"id":312,"unit":"People","order":2,"chartId":303,"property":"y","shortUnit":null,"tolerance":5,"targetYear":null,"variableId":1326,"displayName":"Population in Autocracy","isProjection":false,"conversionFactor":null},{"id":313,"unit":"People","order":3,"chartId":303,"property":"y","shortUnit":null,"tolerance":5,"targetYear":null,"variableId":1327,"displayName":"Population in Closed Anocracy","isProjection":false,"conversionFactor":null},{"id":314,"unit":"People","order":4,"chartId":303,"property":"y","shortUnit":null,"tolerance":5,"targetYear":null,"variableId":1328,"displayName":"Population in Open Anocracy","isProjection":false,"conversionFactor":null},{"id":315,"unit":"People","order":5,"chartId":303,"property":"y","shortUnit":null,"tolerance":5,"targetYear":null,"variableId":1329,"displayName":"Population in Democracy","isProjection":false,"conversionFactor":null}],"entityType":"country","hideLegend":false,"hasChartTab":true,"isPublished":true,"iframe-width":"100%","selectedData":[{"color":"#c8c8c8","index":0,"entityId":355},{"color":"#3f3772","index":1,"entityId":355},{"color":"#ca2628","index":2,"entityId":355},{"color":"#f07f59","index":3,"entityId":355},{"color":"#fceb8c","index":4,"entityId":355},{"color":"#34983f","index":5,"entityId":355}],"iframe-height":"660px","internalNotes":"","addCountryMode":"disabled","activeLegendKeys":null,"group-by-variables":false,"hideRelativeToggle":false,"hideTitleAnnotation":true}